{
"type": "FeatureCollection",
"name": "PSE",
"crs": { "type": "name", "properties": { "name": "urn:ogc:def:crs:OGC:1.3:CRS84" } },
"features": [
{ "type": "Feature", "properties": {}, "geometry": { "type": "Point", "coordinates": [-113.525,53.528 ] } },
{ "type": "Feature", "properties": {}, "geometry": { "type": "Point", "coordinates": [-113.413,53.524] } },
{ "type": "Feature", "properties": {}, "geometry": { "type": "Point", "coordinates": [ -113.451,53.531] } },
{ "type": "Feature", "properties": {}, "geometry": { "type": "Point", "coordinates": [-113.505,53.568] } },
{ "type": "Feature", "properties": {}, "geometry": { "type": "Point", "coordinates": [-113.506,53.547 ] } },
{ "type": "Feature", "properties": {}, "geometry": { "type": "Point", "coordinates": [-113.587,53.54] } },
{ "type": "Feature", "properties": {}, "geometry": { "type": "Point", "coordinates": [-113.632,53.640] } }

]
}
